{
  "title": "NYC Open Data — Most recently updated",
  "generated": "2026-06-20T10:14:46+00:00",
  "items": [
    {
      "id": "gsgx-6efw",
      "name": "Street Construction Permits - Stipulations (2020 - Present)",
      "category": "Transportation",
      "agency": "Department of Transportation (DOT)",
      "updated": "2026-06-20T10:11:47.000Z",
      "created": "2018-12-19T19:33:11.000Z",
      "views": 5046,
      "url": "https://data.cityofnewyork.us/d/gsgx-6efw"
    },
    {
      "id": "i4gi-tjb9",
      "name": "DOT Traffic Speeds",
      "category": "Transportation",
      "agency": "Other / unspecified",
      "updated": "2026-06-20T10:11:07.000Z",
      "created": "2017-04-17T18:31:04.000Z",
      "views": 37593,
      "url": "https://data.cityofnewyork.us/d/i4gi-tjb9"
    },
    {
      "id": "wshr-5vic",
      "name": "Electronics Drop Off Locations in NYC",
      "category": "Environment",
      "agency": "Department of Sanitation (DSNY)",
      "updated": "2026-06-20T10:08:20.000Z",
      "created": "2019-10-21T15:58:03.000Z",
      "views": 17405,
      "url": "https://data.cityofnewyork.us/d/wshr-5vic"
    },
    {
      "id": "9wzr-uhik",
      "name": "Electronics Drop Off Locations in NYC (Map)",
      "category": "Environment",
      "agency": "Department of Sanitation (DSNY)",
      "updated": "2026-06-20T10:08:20.000Z",
      "created": "2019-10-21T16:45:10.000Z",
      "views": 8340,
      "url": "https://data.cityofnewyork.us/d/9wzr-uhik"
    },
    {
      "id": "edk2-vkjh",
      "name": "Pharmaceutical and Syringe Drop-Off Locations in NYC",
      "category": "Environment",
      "agency": "Department of Sanitation (DSNY)",
      "updated": "2026-06-20T10:07:44.000Z",
      "created": "2019-10-21T17:36:57.000Z",
      "views": 3416,
      "url": "https://data.cityofnewyork.us/d/edk2-vkjh"
    },
    {
      "id": "g9pi-q9mx",
      "name": "Pharmaceutical and Syringe Drop-Off Locations in NYC (Map)",
      "category": "Environment",
      "agency": "Department of Sanitation (DSNY)",
      "updated": "2026-06-20T10:07:44.000Z",
      "created": "2019-10-21T18:21:44.000Z",
      "views": 1817,
      "url": "https://data.cityofnewyork.us/d/g9pi-q9mx"
    },
    {
      "id": "a7bv-5698",
      "name": "DSNY Commercial Waste Zones (Map)",
      "category": "Procurement & Contracts",
      "agency": "Department of Sanitation (DSNY)",
      "updated": "2026-06-20T10:06:49.000Z",
      "created": "2020-07-28T19:08:15.000Z",
      "views": 8542,
      "url": "https://data.cityofnewyork.us/d/a7bv-5698"
    },
    {
      "id": "8ev8-jjxq",
      "name": "DSNY Commercial Waste Zones",
      "category": "Procurement & Contracts",
      "agency": "Department of Sanitation (DSNY)",
      "updated": "2026-06-20T10:06:49.000Z",
      "created": "2020-07-28T18:57:33.000Z",
      "views": 6375,
      "url": "https://data.cityofnewyork.us/d/8ev8-jjxq"
    },
    {
      "id": "p32s-yqxq",
      "name": "Historical Driver Application Status",
      "category": "Transportation",
      "agency": "Taxi and Limousine Commission (TLC)",
      "updated": "2026-06-20T10:06:32.000Z",
      "created": "2016-06-16T18:07:19.000Z",
      "views": 19593,
      "url": "https://data.cityofnewyork.us/d/p32s-yqxq"
    },
    {
      "id": "dpec-ucu7",
      "name": "TLC New Driver Application Status",
      "category": "Transportation",
      "agency": "Taxi and Limousine Commission (TLC)",
      "updated": "2026-06-20T10:06:27.000Z",
      "created": "2016-05-17T18:43:43.000Z",
      "views": 1753209,
      "url": "https://data.cityofnewyork.us/d/dpec-ucu7"
    },
    {
      "id": "242c-ru4i",
      "name": "DSNY Special Waste Drop-off Sites",
      "category": "Environment",
      "agency": "Department of Sanitation (DSNY)",
      "updated": "2026-06-20T10:06:01.000Z",
      "created": "2020-07-24T02:27:10.000Z",
      "views": 5320,
      "url": "https://data.cityofnewyork.us/d/242c-ru4i"
    },
    {
      "id": "68qr-38va",
      "name": "Special Waste Drop-Off Sites (Map)",
      "category": "Environment",
      "agency": "Department of Sanitation (DSNY)",
      "updated": "2026-06-20T10:06:01.000Z",
      "created": "2020-07-24T03:14:11.000Z",
      "views": 2831,
      "url": "https://data.cityofnewyork.us/d/68qr-38va"
    },
    {
      "id": "2kdb-mfqb",
      "name": "DSNY Garages (Map)",
      "category": "Environment",
      "agency": "Department of Sanitation (DSNY)",
      "updated": "2026-06-20T10:05:51.000Z",
      "created": "2020-07-23T20:32:15.000Z",
      "views": 9692,
      "url": "https://data.cityofnewyork.us/d/2kdb-mfqb"
    },
    {
      "id": "xw3j-2yxf",
      "name": "DSNY Garages",
      "category": "Environment",
      "agency": "Department of Sanitation (DSNY)",
      "updated": "2026-06-20T10:05:51.000Z",
      "created": "2020-07-23T15:06:34.000Z",
      "views": 4580,
      "url": "https://data.cityofnewyork.us/d/xw3j-2yxf"
    },
    {
      "id": "nfid-uabd",
      "name": "Parking Regulation Locations and Signs",
      "category": "Transportation",
      "agency": "Department of Transportation (DOT)",
      "updated": "2026-06-20T10:01:42.000Z",
      "created": "2022-03-14T13:52:58.000Z",
      "views": 24791,
      "url": "https://data.cityofnewyork.us/d/nfid-uabd"
    },
    {
      "id": "t3jq-9nkf",
      "name": "NYC Agencies and Governance Organizations",
      "category": "Government Operations",
      "agency": "Office of Technology and Innovation (OTI)",
      "updated": "2026-06-20T10:00:08.000Z",
      "created": "2025-09-05T13:06:28.000Z",
      "views": 2850,
      "url": "https://data.cityofnewyork.us/d/t3jq-9nkf"
    },
    {
      "id": "3mf9-qshr",
      "name": "Centerline",
      "category": "Government Operations",
      "agency": "Office of Technology and Innovation (OTI)",
      "updated": "2026-06-20T09:43:34.000Z",
      "created": "2024-12-24T18:25:50.000Z",
      "views": 9497,
      "url": "https://data.cityofnewyork.us/d/3mf9-qshr"
    },
    {
      "id": "inkn-q76z",
      "name": "Centerline",
      "category": "Government Operations",
      "agency": "Office of Technology and Innovation (OTI)",
      "updated": "2026-06-20T09:43:34.000Z",
      "created": "2024-12-24T18:05:11.000Z",
      "views": 8608,
      "url": "https://data.cityofnewyork.us/d/inkn-q76z"
    },
    {
      "id": "gkgs-za6m",
      "name": "DSNY DonateNYC Directory",
      "category": "Environment",
      "agency": "Department of Sanitation (DSNY)",
      "updated": "2026-06-20T09:34:04.000Z",
      "created": "2020-08-20T19:05:54.000Z",
      "views": 4247,
      "url": "https://data.cityofnewyork.us/d/gkgs-za6m"
    },
    {
      "id": "qtrb-nhaa",
      "name": "DSNY DonateNYC Directory (Map)",
      "category": "Environment",
      "agency": "Department of Sanitation (DSNY)",
      "updated": "2026-06-20T09:34:04.000Z",
      "created": "2020-08-20T19:53:04.000Z",
      "views": 1686,
      "url": "https://data.cityofnewyork.us/d/qtrb-nhaa"
    },
    {
      "id": "i2y3-sx2e",
      "name": "Curb Metal Protruding Data",
      "category": "Transportation",
      "agency": "Department of Transportation (DOT)",
      "updated": "2026-06-20T08:00:14.000Z",
      "created": "2019-12-23T15:26:46.000Z",
      "views": 1407,
      "url": "https://data.cityofnewyork.us/d/i2y3-sx2e"
    },
    {
      "id": "kj7g-u4gp",
      "name": "Electric Vehicle (EV) Charging Data - Municipal Lots and Garages",
      "category": "Transportation",
      "agency": "Department of Transportation (DOT)",
      "updated": "2026-06-20T06:15:42.000Z",
      "created": "2024-12-20T17:22:06.000Z",
      "views": 2447,
      "url": "https://data.cityofnewyork.us/d/kj7g-u4gp"
    },
    {
      "id": "5esv-8c3f",
      "name": "TLC Vehicles Involved in Crashes (Local Law 31)",
      "category": "Transportation",
      "agency": "Taxi and Limousine Commission (TLC)",
      "updated": "2026-06-20T04:16:12.000Z",
      "created": "2024-12-11T20:12:43.000Z",
      "views": 1795,
      "url": "https://data.cityofnewyork.us/d/5esv-8c3f"
    },
    {
      "id": "erm2-nwe9",
      "name": "311 Service Requests from 2020 to Present",
      "category": "Social Services",
      "agency": "311",
      "updated": "2026-06-20T01:37:31.000Z",
      "created": "2011-10-10T05:52:17.000Z",
      "views": 1248415,
      "url": "https://data.cityofnewyork.us/d/erm2-nwe9"
    },
    {
      "id": "jwvp-gyiq",
      "name": "DOT Street Lights and Traffic Signals (311 Service Requests from 2010 to Present)",
      "category": "Transportation",
      "agency": "311",
      "updated": "2026-06-20T01:37:31.000Z",
      "created": "2017-10-25T20:28:13.000Z",
      "views": 9951,
      "url": "https://data.cityofnewyork.us/d/jwvp-gyiq"
    },
    {
      "id": "wewp-mm3p",
      "name": "311 Call Center Inquiry",
      "category": "Government Operations",
      "agency": "311",
      "updated": "2026-06-20T01:03:36.000Z",
      "created": "2016-05-12T22:58:27.000Z",
      "views": 18510,
      "url": "https://data.cityofnewyork.us/d/wewp-mm3p"
    },
    {
      "id": "ipu4-2q9a",
      "name": "DOB Permit Issuance",
      "category": "Housing & Development",
      "agency": "Department of Buildings (DOB)",
      "updated": "2026-06-20T01:03:09.000Z",
      "created": "2013-04-18T15:18:56.000Z",
      "views": 598508,
      "url": "https://data.cityofnewyork.us/d/ipu4-2q9a"
    },
    {
      "id": "gy3q-4tzp",
      "name": "Active NYC Health Code Regulated Child Care Programs",
      "category": "Health",
      "agency": "Department of Health and Mental Hygiene (DOHMH)",
      "updated": "2026-06-19T23:00:19.000Z",
      "created": "2023-11-02T18:27:26.000Z",
      "views": 3519,
      "url": "https://data.cityofnewyork.us/d/gy3q-4tzp"
    },
    {
      "id": "jz4z-kudi",
      "name": "OATH Hearings Division Case Status",
      "category": "Government Operations",
      "agency": "Office of Administrative Trials and Hearings (OATH)",
      "updated": "2026-06-19T22:49:39.000Z",
      "created": "2013-08-19T14:01:01.000Z",
      "views": 392590,
      "url": "https://data.cityofnewyork.us/d/jz4z-kudi"
    },
    {
      "id": "43nn-pn8j",
      "name": "DOHMH New York City Restaurant Inspection Results",
      "category": "Health",
      "agency": "Department of Health and Mental Hygiene (DOHMH)",
      "updated": "2026-06-19T22:07:14.000Z",
      "created": "2014-08-01T19:10:59.000Z",
      "views": 400020,
      "url": "https://data.cityofnewyork.us/d/43nn-pn8j"
    },
    {
      "id": "rdxc-q253",
      "name": "Street Hail Livery (SHL) Taxi Initial Inspection Schedule",
      "category": "Transportation",
      "agency": "Taxi and Limousine Commission (TLC)",
      "updated": "2026-06-19T22:03:54.000Z",
      "created": "2017-03-21T21:48:56.000Z",
      "views": 7812,
      "url": "https://data.cityofnewyork.us/d/rdxc-q253"
    },
    {
      "id": "eccv-9dzr",
      "name": "CURRENT BASES",
      "category": "Transportation",
      "agency": "Taxi and Limousine Commission (TLC)",
      "updated": "2026-06-19T22:03:27.000Z",
      "created": "2015-04-21T17:43:01.000Z",
      "views": 122051,
      "url": "https://data.cityofnewyork.us/d/eccv-9dzr"
    },
    {
      "id": "2v9c-2k7f",
      "name": "FHV Base Aggregate Report",
      "category": "Transportation",
      "agency": "Taxi and Limousine Commission (TLC)",
      "updated": "2026-06-19T22:03:20.000Z",
      "created": "2016-04-07T16:15:02.000Z",
      "views": 152874,
      "url": "https://data.cityofnewyork.us/d/2v9c-2k7f"
    },
    {
      "id": "ht4t-wzcm",
      "name": "Taxi Improvement Fund (TIF) Medallion Payments",
      "category": "Transportation",
      "agency": "Taxi and Limousine Commission (TLC)",
      "updated": "2026-06-19T22:02:55.000Z",
      "created": "2016-11-17T14:57:46.000Z",
      "views": 21668,
      "url": "https://data.cityofnewyork.us/d/ht4t-wzcm"
    },
    {
      "id": "ic3t-wcy2",
      "name": "DOB Job Application Filings",
      "category": "Housing & Development",
      "agency": "Department of Buildings (DOB)",
      "updated": "2026-06-19T21:55:28.000Z",
      "created": "2013-04-18T15:18:56.000Z",
      "views": 2426240,
      "url": "https://data.cityofnewyork.us/d/ic3t-wcy2"
    },
    {
      "id": "dm9a-ab7w",
      "name": "DOB NOW: Electrical Permit Applications",
      "category": "Government Operations",
      "agency": "Department of Buildings (DOB)",
      "updated": "2026-06-19T21:45:19.000Z",
      "created": "2019-04-17T16:07:21.000Z",
      "views": 26324,
      "url": "https://data.cityofnewyork.us/d/dm9a-ab7w"
    },
    {
      "id": "x2s6-6d2j",
      "name": "DEP - Cryptosporidium And Giardia Data Set",
      "category": "Environment",
      "agency": "Department of Environmental Protection (DEP)",
      "updated": "2026-06-19T21:00:31.000Z",
      "created": "2014-03-04T22:28:23.000Z",
      "views": 6298,
      "url": "https://data.cityofnewyork.us/d/x2s6-6d2j"
    },
    {
      "id": "tqtj-sjs8",
      "name": "Street Construction Permits (2022 - Present)",
      "category": "Transportation",
      "agency": "Department of Transportation (DOT)",
      "updated": "2026-06-19T20:44:21.000Z",
      "created": "2018-12-17T18:27:24.000Z",
      "views": 51115,
      "url": "https://data.cityofnewyork.us/d/tqtj-sjs8"
    },
    {
      "id": "tb8q-a3ar",
      "name": "Order to Repair/Vacate Orders",
      "category": "Housing & Development",
      "agency": "Department of Housing Preservation and Development (HPD)",
      "updated": "2026-06-19T20:40:18.000Z",
      "created": "2018-03-05T20:56:41.000Z",
      "views": 22475,
      "url": "https://data.cityofnewyork.us/d/tb8q-a3ar"
    },
    {
      "id": "bs8b-p36w",
      "name": "DOB Certificate Of Occupancy",
      "category": "Housing & Development",
      "agency": "Other / unspecified",
      "updated": "2026-06-19T20:36:16.000Z",
      "created": "2017-06-30T19:26:39.000Z",
      "views": 79749,
      "url": "https://data.cityofnewyork.us/d/bs8b-p36w"
    },
    {
      "id": "9cw8-7heb",
      "name": ".nyc Domain Registrations",
      "category": "Business",
      "agency": "Office of Technology and Innovation (OTI)",
      "updated": "2026-06-19T20:33:52.000Z",
      "created": "2015-07-13T18:48:56.000Z",
      "views": 10910,
      "url": "https://data.cityofnewyork.us/d/9cw8-7heb"
    },
    {
      "id": "e5aq-a4j2",
      "name": "DOB NOW Elevator Safety Compliance",
      "category": "Housing & Development",
      "agency": "Department of Buildings (DOB)",
      "updated": "2026-06-19T20:33:04.000Z",
      "created": "2023-01-27T20:04:44.000Z",
      "views": 8336,
      "url": "https://data.cityofnewyork.us/d/e5aq-a4j2"
    },
    {
      "id": "w9ak-ipjd",
      "name": "DOB NOW: Build – Job Application Filings",
      "category": "Housing & Development",
      "agency": "Department of Buildings (DOB)",
      "updated": "2026-06-19T20:26:46.000Z",
      "created": "2016-05-26T13:34:09.000Z",
      "views": 147877,
      "url": "https://data.cityofnewyork.us/d/w9ak-ipjd"
    },
    {
      "id": "t8hj-ruu2",
      "name": "DOB License Info",
      "category": "Housing & Development",
      "agency": "Other / unspecified",
      "updated": "2026-06-19T20:13:15.000Z",
      "created": "2017-06-08T16:41:22.000Z",
      "views": 30108,
      "url": "https://data.cityofnewyork.us/d/t8hj-ruu2"
    },
    {
      "id": "xmmq-y7za",
      "name": "DOB NOW: Electrical Permit Details",
      "category": "Government Operations",
      "agency": "Department of Buildings (DOB)",
      "updated": "2026-06-19T20:09:16.000Z",
      "created": "2019-04-17T16:43:07.000Z",
      "views": 10044,
      "url": "https://data.cityofnewyork.us/d/xmmq-y7za"
    },
    {
      "id": "pkdm-hqz6",
      "name": "DOB NOW: Certificate of Occupancy",
      "category": "Housing & Development",
      "agency": "Department of Buildings (DOB)",
      "updated": "2026-06-19T20:02:55.000Z",
      "created": "2022-05-17T17:24:15.000Z",
      "views": 17780,
      "url": "https://data.cityofnewyork.us/d/pkdm-hqz6"
    },
    {
      "id": "i296-73x5",
      "name": "DOB Stalled Construction Sites",
      "category": "Housing & Development",
      "agency": "Department of Buildings (DOB)",
      "updated": "2026-06-19T20:01:24.000Z",
      "created": "2013-04-18T15:19:09.000Z",
      "views": 21152,
      "url": "https://data.cityofnewyork.us/d/i296-73x5"
    },
    {
      "id": "cspg-yi7g",
      "name": "Construction Demolition Registrants",
      "category": "Government Operations",
      "agency": "Business Integrity Commission (BIC)",
      "updated": "2026-06-19T19:50:42.000Z",
      "created": "2017-03-10T20:42:45.000Z",
      "views": 33568,
      "url": "https://data.cityofnewyork.us/d/cspg-yi7g"
    },
    {
      "id": "a8wp-rerh",
      "name": "Self Hauler Registrants",
      "category": "Government Operations",
      "agency": "Business Integrity Commission (BIC)",
      "updated": "2026-06-19T19:50:38.000Z",
      "created": "2017-03-10T21:05:31.000Z",
      "views": 33325,
      "url": "https://data.cityofnewyork.us/d/a8wp-rerh"
    },
    {
      "id": "krx7-u82t",
      "name": "Trade Waste Broker Registrants",
      "category": "Government Operations",
      "agency": "Business Integrity Commission (BIC)",
      "updated": "2026-06-19T19:50:33.000Z",
      "created": "2017-03-28T18:10:06.000Z",
      "views": 24407,
      "url": "https://data.cityofnewyork.us/d/krx7-u82t"
    }
  ]
}