{
  "computed_at": "2026-05-29T10:34:08+00:00",
  "window_start": "2026-05-22T10:34:08",
  "window_label": "the past 7 days",
  "trend_weeks": 12,
  "stats": [
    {
      "key": "311",
      "headline": "49,617",
      "label": "311 complaints in the past 7 days",
      "sub": "Most common: Illegal Parking (7,310)",
      "trend": [
        79199,
        77420,
        75174,
        74286,
        66762,
        73671,
        71670,
        69360,
        72549,
        72016,
        82220,
        49617
      ],
      "delta_pct": -40,
      "dataset_id": "erm2-nwe9",
      "dataset_name": "311 Service Requests from 2020 to Present",
      "category": "Social Services"
    },
    {
      "key": "mvc",
      "headline": "729",
      "label": "Motor-vehicle crashes reported",
      "sub": "300 people injured",
      "trend": [
        1238,
        1509,
        1486,
        1574,
        1411,
        1598,
        1584,
        1637,
        1706,
        1592,
        1736,
        729
      ],
      "delta_pct": -58,
      "dataset_id": "h9gi-nx95",
      "dataset_name": "Motor Vehicle Collisions - Crashes",
      "category": "Public Safety"
    },
    {
      "key": "dob",
      "headline": "2,266",
      "label": "DOB construction permits issued",
      "sub": "Excludes electrical and elevator filings",
      "trend": [
        3007,
        3943,
        3585,
        3902,
        3175,
        3045,
        3733,
        3742,
        3288,
        3622,
        3643,
        2266
      ],
      "delta_pct": -38,
      "dataset_id": "rbx6-tga4",
      "dataset_name": "DOB NOW: Build – Approved Permits",
      "category": "Housing & Development"
    },
    {
      "key": "rest",
      "headline": "537",
      "label": "Restaurant inspections completed",
      "sub": "30% earned an A grade (101 of 339 graded)",
      "trend": [
        1563,
        1585,
        1917,
        2103,
        2000,
        1928,
        2185,
        2326,
        2424,
        2176,
        1927,
        537
      ],
      "delta_pct": -72,
      "dataset_id": "43nn-pn8j",
      "dataset_name": "DOHMH NYC Restaurant Inspection Results",
      "category": "Health"
    },
    {
      "key": "catalog",
      "headline": "257",
      "label": "Datasets refreshed by City agencies",
      "sub": "3,014 total datasets in the catalog",
      "trend": [
        13,
        32,
        19,
        26,
        8,
        20,
        23,
        149,
        66,
        84,
        148,
        257
      ],
      "delta_pct": 74,
      "dataset_id": null,
      "dataset_name": "NYC Open Data catalog metadata",
      "category": null
    }
  ],
  "errors": []
}